arg_needle_lib_pybind.cpython-310-darwin.so
arg_needle_lib/metrics.py
arg_needle_lib/convert.py
arg_needle_lib/constants.py
arg_needle_lib/__init__.py
arg_needle_lib/grm.py
arg_needle_lib/serialize_arg.py
arg_needle_lib/.dylibs/libhdf5.310.5.1.dylib
arg_needle_lib/.dylibs/libaec.0.1.4.dylib
arg_needle_lib/.dylibs/libhdf5_cpp.310.0.6.dylib
arg_needle_lib/.dylibs/libboost_iostreams.dylib
arg_needle_lib/.dylibs/libicudata.77.1.dylib
arg_needle_lib/.dylibs/libicuuc.77.1.dylib
arg_needle_lib/.dylibs/libboost_random.dylib
arg_needle_lib/.dylibs/libboost_regex.dylib
arg_needle_lib/.dylibs/libsz.2.0.1.dylib
arg_needle_lib/.dylibs/liblzma.5.dylib
arg_needle_lib/.dylibs/libicui18n.77.1.dylib
arg_needle_lib/.dylibs/libzstd.1.5.7.dylib
arg_needle_lib/scripts/convert.py
arg_needle_lib/scripts/__init__.py
arg_needle_lib/scripts/association.py
arg_needle_lib/scripts/prepare_association_example.py
arg_needle_lib-1.2.1.dist-info/RECORD
arg_needle_lib-1.2.1.dist-info/WHEEL
arg_needle_lib-1.2.1.dist-info/entry_points.txt
arg_needle_lib-1.2.1.dist-info/METADATA
arg_needle_lib-1.2.1.dist-info/licenses/LICENSE
