Metadata-Version: 2.2
Name: arg-needle-lib
Version: 1.2.1
Summary: Ancestral recombination graph (ARG) data structure and operations
Author: ARG-Needle Developers
Classifier: Development Status :: 4 - Beta
Classifier: License :: OSI Approved :: GNU General Public License v3 or later (GPLv3+)
Classifier: Programming Language :: Python :: 3 :: Only
Classifier: Programming Language :: Python :: 3.9
Classifier: Programming Language :: Python :: 3.10
Classifier: Programming Language :: Python :: 3.11
Classifier: Programming Language :: Python :: 3.12
Classifier: Programming Language :: Python :: 3.13
Requires-Python: >=3.9
Requires-Dist: click
Requires-Dist: h5py
Requires-Dist: msprime>=1.3.0
Requires-Dist: pandas
Requires-Dist: scipy
Requires-Dist: tskit>=0.5.8
Provides-Extra: dev
Requires-Dist: pytest; extra == "dev"
Requires-Dist: tszip>=0.2.5; extra == "dev"
Provides-Extra: docs
Requires-Dist: sphinx; extra == "docs"
Requires-Dist: sphinx-rtd-theme; extra == "docs"
